LICENSE
README.md
pyproject.toml
setup.py
ib_core/__init__.py
ib_core/admin.py
ib_core/apps.py
ib_core/fields.py
ib_core/models.py
ib_core.egg-info/PKG-INFO
ib_core.egg-info/SOURCES.txt
ib_core.egg-info/dependency_links.txt
ib_core.egg-info/requires.txt
ib_core.egg-info/top_level.txt
ib_core/filtering/__init__.py
ib_core/filtering/models.py
ib_core/filtering/types.py
ib_core/migrations/0001_initial.py
ib_core/migrations/0002_remove_tagbinder_creator_and_more.py
ib_core/migrations/0003_activityperiod.py
ib_core/migrations/0004_activityperiod_deleted.py
ib_core/migrations/__init__.py
ib_core/mixins/__init__.py
ib_core/mixins/authorization.py
ib_core/pagination/__init__.py
ib_core/pagination/paginators.py
ib_core/serializers/__init__.py
ib_core/serializers/common.py
ib_core/serializers/instance_serializers.py
ib_core/serializers/tag_binder_serializers.py
ib_core/tags/__init__.py
ib_core/tags/manage.py
ib_core/tokens/__init__.py
ib_core/tokens/auth_types.py
ib_core/tokens/models.py
ib_core/tokens/types.py
ib_core/utils/__init__.py
ib_core/utils/authorization.py
ib_core/utils/urls_manager.py
ib_core/utils/uuid_manager.py
ib_core/views/__init__.py
ib_core/views/creating.py
ib_core/views/deleting.py
ib_core/views/getting.py
ib_core/views/tags.py