Metadata-Version: 2.1
Name: ib-core
Version: 1.0.1
Summary: Integration Bus django-applications core
Home-page: https://gitlab.it-psg.com/ib-elp-it-psg/ib_core
Download-URL: https://gitlab.it-psg.com/ib-elp-it-psg/ib_core.git
Author: Damir Fatkhullin
Author-email: damir.f@it-psg.com
License: MIT
Classifier: License :: OSI Approved :: MIT License
Classifier: Programming Language :: Python :: 2.7
Classifier: Programming Language :: Python :: 3.4
Classifier: Programming Language :: Python :: 3.5
License-File: LICENSE
Requires-Dist: django
Requires-Dist: djangorestframework
Requires-Dist: requests
